compPy/.DS_Store
compPy/__init__.py
compPy/align.py
compPy/compute_speed.py
compPy/compute_waveang.py
compPy/load_defaults.py
compPy/space_time_run.py
compPy/density/__init__.py
compPy/density/density.py
compPy/developments/compute_speed_old.py
compPy/developments/compute_waveang_dev_v2.py
compPy/developments/compute_waveang_old.py
compPy/developments/velocity_calc.py
compPy/io/__init__.py
compPy/io/in_out.py
compPy/io/save_load.py
compPy/tests/test_io.py
compPy/tests/test_load_defaults.py
compPy/tests/test_util.py
compPy/util/__init__.py
compPy/util/config.py
compPy/util/do_apod.py
compPy/util/filter_funcs.py
compPy/util/intensity_filler.py
compPy/util/map_tools.py
compPy/util/spectraldensity.py
compPy/util/util.py
compPy-0.1.3.dist-info/LICENSE
compPy-0.1.3.dist-info/METADATA
compPy-0.1.3.dist-info/WHEEL
compPy-0.1.3.dist-info/top_level.txt
compPy-0.1.3.dist-info/RECORD
